main.py
otobo_demo-0.1.7.dist-info/METADATA
otobo_demo-0.1.7.dist-info/WHEEL
otobo_demo-0.1.7.dist-info/top_level.txt
otobo_demo-0.1.7.dist-info/RECORD
