Metadata-Version: 2.4
Name: otobo-demo
Version: 0.1.7
Summary: Add your description here
Requires-Python: >=3.13
Requires-Dist: open-ticket-ai>=1.0.12
Requires-Dist: otai-hf-local>=1.0.1
Requires-Dist: otai-otobo-znuny>=1.0.1
